{
  "$type": "Comindware.Platform.Contracts.ToolbarModel, Comindware.Platform.Contracts",
  "GlobalAlias": {
    "$type": "Comindware.Platform.Contracts.GlobalAlias, Comindware.Platform.Contracts",
    "Type": "Toolbar",
    "Owner": "exchange",
    "Alias": "defaultDiagramToolbar"
  },
  "Name": "Панель инструментов для диаграммы процесса",
  "IsDefaultForLists": false,
  "IsDefaultForForms": false,
  "IsDefaultForProcess": false,
  "Items": {
    "$type": "System.Collections.Generic.List`1[[Comindware.Platform.Contracts.ToolbarItemModel, Comindware.Platform.Contracts]], mscorlib",
    "$values": [
      {
        "$type": "Comindware.Platform.Contracts.ToolbarItemModel, Comindware.Platform.Contracts",
        "UserCommandGlobalAlias": {
          "$type": "Comindware.Platform.Contracts.GlobalAlias, Comindware.Platform.Contracts",
          "Type": "UserCommand",
          "Owner": "exchange",
          "Alias": "editDiagram"
        },
        "Name": "Начать редактирование",
        "Order": 0,
        "Type": "Action",
        "IconType": "Undefined",
        "Severity": "None"
      }
    ]
  }
}